etc/fackup.yml.example
fackup/__init__.py
fackup/args.py
fackup/cmd.py
fackup/config.py
fackup/core.py
fackup/dar.py
fackup/exceptions.py
fackup/log.py
fackup/rsync.py
fackup-0.1.4.dist-info/LICENSE
fackup-0.1.4.dist-info/METADATA
fackup-0.1.4.dist-info/WHEEL
fackup-0.1.4.dist-info/entry_points.txt
fackup-0.1.4.dist-info/top_level.txt
fackup-0.1.4.dist-info/RECORD
