Metadata-Version: 2.1
Name: fackup
Version: 0.1.4
Summary: File backup tool using rsync and dar.
Home-page: https://github.com/b3niup/fackup
Author: Benedykt Przybyło
Author-email: b3niup@gmail.com
License: UNKNOWN
Keywords: backup dar rsync
Platform: UNKNOWN
Classifier: Development Status :: 3 - Alpha
Classifier: Environment :: Console
Classifier: Intended Audience :: Developers
Classifier: Intended Audience :: End Users/Desktop
Classifier: Intended Audience :: System Administrators
Classifier: License :: OSI Approved :: MIT License
Classifier: Operating System :: POSIX
Classifier: Programming Language :: Python :: 3.4
Classifier: Topic :: System :: Archiving :: Backup
Classifier: Topic :: System :: Systems Administration
License-File: LICENSE
Requires-Dist: PyYAML (>=3.0)
